{"cameraMode":{"drawMode":0,"name":"Shaded","section":"Shading Mode"},"sceneLighting":true,"audioPlay":false,"sceneViewState":{"m_AlwaysRefresh":false,"showFog":true,"showSkybox":true,"showFlares":true,"showImageEffects":true,"showParticleSystems":true,"showVisualEffectGraphs":true,"m_FxEnabled":true},"in2DMode":false,"pivot":{"x":0.5674465894699097,"y":8.547272682189942,"z":0.04733467102050781},"rotation":{"x":0.05179932340979576,"y":0.02367324009537697,"z":0.0068128397688269619,"w":0.9983857274055481},"size":15.713932037353516,"orthographic":false}